pycsamt/__init__.py
pycsamt/__main__.py
pycsamt/_csamtpylog.py
pycsamt/_path.py
pycsamt/bases.py
pycsamt/site.py
pycsamt/cli/__init__.py
pycsamt/cli/avg2edi.py
pycsamt/cli/correctedi.py
pycsamt/cli/fitforward.py
pycsamt/cli/j2edi.py
pycsamt/cli/misfit2d.py
pycsamt/cli/myconfigfile.py
pycsamt/cli/nm.py
pycsamt/cli/occambuildinputs.py
pycsamt/cli/penetration1d.py
pycsamt/cli/penetration2d.py
pycsamt/cli/pseudocrossresistivityandphase.py
pycsamt/cli/pseudostratigraphic.py
pycsamt/cli/rewriteedi.py
pycsamt/cli/rms.py
pycsamt/cli/staticshift.py
pycsamt/core/__init__.py
pycsamt/core/avg.py
pycsamt/core/cs.py
pycsamt/core/edi.py
pycsamt/core/j.py
pycsamt/core/wfem.py
pycsamt/core/z.py
pycsamt/geodrill/__init__.py
pycsamt/geodrill/_dictapp.py
pycsamt/geodrill/geocore.py
pycsamt/geodrill/geodatabase.py
pycsamt/geodrill/ml.py
pycsamt/geodrill/requestmanager.py
pycsamt/geodrill/strata.py
pycsamt/geodrill/structural.py
pycsamt/geodrill/update_upgrade_geoDataBase.py
pycsamt/geodrill/_geocodes/AGSO.csv
pycsamt/geodrill/_geocodes/AGSO_STCODES.csv
pycsamt/geodrill/_geocodes/__memory.pkl
pycsamt/geodrill/_geomemo/__m.sq3
pycsamt/geodrill/_geomemo/memory.sq3
pycsamt/gui/__init__.py
pycsamt/gui/cmake_dh.py
pycsamt/gui/corrected_edi.py
pycsamt/gui/gs2f.py
pycsamt/gui/gui_avgapp.py
pycsamt/gui/gui_frames.py
pycsamt/gui/maingui.py
pycsamt/gui/oas2f.py
pycsamt/gui/oc2d_bdin.py
pycsamt/gui/p2log.py
pycsamt/gui/p_moc2d.py
pycsamt/gui/personal_frames.py
pycsamt/gui/wa2edi.py
pycsamt/gui/wa2j.py
pycsamt/gui/wi2d.py
pycsamt/gui/wrap_console_scripts.py
pycsamt/gui/write_avg2j.py
pycsamt/metadata/e.g.data.json
pycsamt/metadata/e.g.data.yml
pycsamt/modeling/__init__.py
pycsamt/modeling/modem.py
pycsamt/modeling/occam2d.py
pycsamt/processing/__init__.py
pycsamt/processing/corr.py
pycsamt/processing/ctools.py
pycsamt/utils/__init__.py
pycsamt/utils/_p.py
pycsamt/utils/_set_gdal.py
pycsamt/utils/avg_utils.py
pycsamt/utils/decorator.py
pycsamt/utils/exceptions.py
pycsamt/utils/func_utils.py
pycsamt-1.2.1.dist-info/LICENSE.md
pycsamt-1.2.1.dist-info/METADATA
pycsamt-1.2.1.dist-info/WHEEL
pycsamt-1.2.1.dist-info/entry_points.txt
pycsamt-1.2.1.dist-info/top_level.txt
pycsamt-1.2.1.dist-info/RECORD
