Metadata-Version: 2.1
Name: pycsamt
Version: 1.2.1
Summary: A Python open-source toolkit Audio-frequency Magnetotelluric 
Home-page: https://github.com/WEgeophysics/pyCSAMT
Author: Kouadio K. Laurent,  Rong Liu,  Binbin Mi,  Chum-ning Liu,  Albert O. Malory.
Author-email: kkouao@zju.edu.cn
Maintainer: Kouadio K. Laurent
Maintainer-email: etanoyau@gmail.com
License: GNU LESSER GENERAL PUBLIC LICENSE v3
Project-URL: API Documentation, https://pycsamt.readthedocs.io/en/master/
Project-URL: Home page, https://github.com/WEgeophysics/pyCSAMT/wiki
Project-URL: Bugs tracker, https://github.com/WEgeophysics/pyCSAMT/issues
Project-URL: Installation guide, https://github.com/WEgeophysics/pyCSAMT/wiki/pyCSAMT-installation-guide-for-Windows--and-Linux
Project-URL: User guide, https://github.com/WEgeophysics/pyCSAMT/blob/develop/docs/pyCSAMT%20User%20Guide.pdf
Keywords: hydrogeophysic,groundwater,exploration,csamt
Classifier: Development Status :: 3 - Alpha
Classifier: Intended Audience :: Science/Research
Classifier: Topic :: Software Development
Classifier: Topic :: Scientific/Engineering
Classifier: Programming Language :: Python :: 3.7
Classifier: Programming Language :: Python :: 3.8
Classifier: Programming Language :: Python :: 3.9
Classifier: Operating System :: OS Independent
Requires-Python: >=3.7
License-File: LICENSE.md
Requires-Dist: numpy (>=1.8.1)
Requires-Dist: scipy (>=0.14.0)
Requires-Dist: matplotlib
Requires-Dist: mtpy (>=1.1.0)
Requires-Dist: pyyaml
Requires-Dist: pyproj
Requires-Dist: configparser
Requires-Dist: tqdm
